zj_utils/__init__.py
zj_utils/concurrency.py
zj_utils/files.py
zj_utils/helper.py
zj_utils/pdf.py
zj_utils/timer.py
zj_utils/video.py
zj_utils_zjj421-0.0.22.dist-info/LICENSE
zj_utils_zjj421-0.0.22.dist-info/METADATA
zj_utils_zjj421-0.0.22.dist-info/WHEEL
zj_utils_zjj421-0.0.22.dist-info/top_level.txt
zj_utils_zjj421-0.0.22.dist-info/RECORD
